pandaprint/__init__.py
pandaprint/server.py
pandaprint-1.0.0.dist-info/LICENSE.txt
pandaprint-1.0.0.dist-info/METADATA
pandaprint-1.0.0.dist-info/WHEEL
pandaprint-1.0.0.dist-info/entry_points.txt
pandaprint-1.0.0.dist-info/RECORD
