Metadata-Version: 2.1
Name: pandaprint
Version: 1.0.0
Summary: 
Author: James E. Blair
Author-email: corvus@gnu.org
Requires-Python: >=3.12,<4.0
Classifier: Programming Language :: Python :: 3
Classifier: Programming Language :: Python :: 3.12
Requires-Dist: cherrypy (>=18.10.0,<19.0.0)
Requires-Dist: paho-mqtt (>=2.1.0,<3.0.0)
Requires-Dist: pbr (>=6.1.0,<7.0.0)
Requires-Dist: pyyaml (>=6.0.2,<7.0.0)
Requires-Dist: routes (>=2.5.1,<3.0.0)
